{
    "type": "ENTITY",
    "data": [
        {
            "name": "曲沃县",
            "cityId": {
                "$REF$": "(lct.city,name=临汾市)"
            }
        },
        {
            "name": "侯马市",
            "cityId": {
                "$REF$": "(lct.city,name=临汾市)"
            }
        },
        {
            "name": "霍州市",
            "cityId": {
                "$REF$": "(lct.city,name=临汾市)"
            }
        },
        {
            "name": "汾西县",
            "cityId": {
                "$REF$": "(lct.city,name=临汾市)"
            }
        },
        {
            "name": "吉县",
            "cityId": {
                "$REF$": "(lct.city,name=临汾市)"
            }
        },
        {
            "name": "安泽县",
            "cityId": {
                "$REF$": "(lct.city,name=临汾市)"
            }
        },
        {
            "name": "浮山县",
            "cityId": {
                "$REF$": "(lct.city,name=临汾市)"
            }
        },
        {
            "name": "大宁县",
            "cityId": {
                "$REF$": "(lct.city,name=临汾市)"
            }
        },
        {
            "name": "古县",
            "cityId": {
                "$REF$": "(lct.city,name=临汾市)"
            }
        },
        {
            "name": "隰县",
            "cityId": {
                "$REF$": "(lct.city,name=临汾市)"
            }
        },
        {
            "name": "襄汾县",
            "cityId": {
                "$REF$": "(lct.city,name=临汾市)"
            }
        },
        {
            "name": "翼城县",
            "cityId": {
                "$REF$": "(lct.city,name=临汾市)"
            }
        },
        {
            "name": "永和县",
            "cityId": {
                "$REF$": "(lct.city,name=临汾市)"
            }
        },
        {
            "name": "乡宁县",
            "cityId": {
                "$REF$": "(lct.city,name=临汾市)"
            }
        },
        {
            "name": "洪洞县",
            "cityId": {
                "$REF$": "(lct.city,name=临汾市)"
            }
        },
        {
            "name": "蒲县",
            "cityId": {
                "$REF$": "(lct.city,name=临汾市)"
            }
        },
        {
            "name": "尧都区",
            "cityId": {
                "$REF$": "(lct.city,name=临汾市)"
            }
        }
    ]
}