{
    "type": "ENTITY",
    "data": [
        {
            "name": "县城内",
            "cityId":{
                "$REF$":"(lct.city,name=武隆县)"
            }
        },
        {
            "name": "仙女山镇",
            "cityId":{
                "$REF$":"(lct.city,name=武隆县)"
            }
        },
        {
            "name": "巷口镇",
            "cityId":{
                "$REF$":"(lct.city,name=武隆县)"
            }
        },
        {
            "name": "白马镇",
            "cityId":{
                "$REF$":"(lct.city,name=武隆县)"
            }
        },
        {
            "name": "火炉镇",
            "cityId":{
                "$REF$":"(lct.city,name=武隆县)"
            }
        },
        {
            "name": "江口镇",
            "cityId":{
                "$REF$":"(lct.city,name=武隆县)"
            }
        },
        {
            "name": "平桥镇",
            "cityId":{
                "$REF$":"(lct.city,name=武隆县)"
            }
        },
        {
            "name": "桐梓镇",
            "cityId":{
                "$REF$":"(lct.city,name=武隆县)"
            }
        },
        {
            "name": "土坎镇",
            "cityId":{
                "$REF$":"(lct.city,name=武隆县)"
            }
        },
        {
            "name": "鸭江镇",
            "cityId":{
                "$REF$":"(lct.city,name=武隆县)"
            }
        },
        {
            "name": "羊角镇",
            "cityId":{
                "$REF$":"(lct.city,name=武隆县)"
            }
        },
        {
            "name": "长坝镇",
            "cityId":{
                "$REF$":"(lct.city,name=武隆县)"
            }
        },
        {
            "name": "白云乡",
            "cityId":{
                "$REF$":"(lct.city,name=武隆县)"
            }
        },
        {
            "name": "沧沟乡",
            "cityId":{
                "$REF$":"(lct.city,name=武隆县)"
            }
        },
        {
            "name": "凤来乡",
            "cityId":{
                "$REF$":"(lct.city,name=武隆县)"
            }
        },
        {
            "name": "浩口乡",
            "cityId":{
                "$REF$":"(lct.city,name=武隆县)"
            }
        },
        {
            "name": "和顺乡",
            "cityId":{
                "$REF$":"(lct.city,name=武隆县)"
            }
        },
        {
            "name": "后坪乡",
            "cityId":{
                "$REF$":"(lct.city,name=武隆县)"
            }
        },
        {
            "name": "黄莺乡",
            "cityId":{
                "$REF$":"(lct.city,name=武隆县)"
            }
        },
        {
            "name": "接龙乡",
            "cityId":{
                "$REF$":"(lct.city,name=武隆县)"
            }
        },
        {
            "name": "庙垭乡",
            "cityId":{
                "$REF$":"(lct.city,name=武隆县)"
            }
        },
        {
            "name": "石桥乡",
            "cityId":{
                "$REF$":"(lct.city,name=武隆县)"
            }
        },
        {
            "name": "双河乡",
            "cityId":{
                "$REF$":"(lct.city,name=武隆县)"
            }
        },
        {
            "name": "铁矿乡",
            "cityId":{
                "$REF$":"(lct.city,name=武隆县)"
            }
        },
        {
            "name": "土地乡",
            "cityId":{
                "$REF$":"(lct.city,name=武隆县)"
            }
        },
        {
            "name": "文复乡",
            "cityId":{
                "$REF$":"(lct.city,name=武隆县)"
            }
        },
        {
            "name": "赵家乡",
            "cityId":{
                "$REF$":"(lct.city,name=武隆县)"
            }
        }
    ]
}
